openssl_gtk/__init__.py
openssl_gtk/app_info.py
openssl_gtk/logo.png
openssl_gtk/thread.py
openssl_gtk/window.py
openssl_gtk-1.1.1.data/scripts/openssl-gui.py
openssl_gtk-1.1.1.dist-info/LICENSE
openssl_gtk-1.1.1.dist-info/LICENSE_TR
openssl_gtk-1.1.1.dist-info/METADATA
openssl_gtk-1.1.1.dist-info/WHEEL
openssl_gtk-1.1.1.dist-info/top_level.txt
openssl_gtk-1.1.1.dist-info/RECORD
