Metadata-Version: 2.1
Name: openssl-gtk
Version: 1.1.1
Summary: Perform your Openssl operations without using a terminal.
Home-page: https://github.com/muhammedcamsari/openssl-gtk
Author: Muhammed Çamsarı
Author-email: Muhammedcamsari@icloud.com
License: MIT
Keywords: openssl,openssl-gui,security,encrypt
Platform: UNKNOWN
Classifier: Development Status :: 4 - Beta
Classifier: Programming Language :: Python :: 3
Classifier: License :: OSI Approved :: MIT License
Classifier: Intended Audience :: End Users/Desktop
Classifier: Topic :: Desktop Environment :: Gnome
Classifier: Natural Language :: Turkish
Classifier: Operating System :: OS Independent
Requires-Dist: opy-logger (>=2.0)
